wangph/__init__.py
wangph/helloworld.py
wangph/math.py
wangph/math_util.py
wangph-0.0.2.dist-info/LICENSE
wangph-0.0.2.dist-info/METADATA
wangph-0.0.2.dist-info/WHEEL
wangph-0.0.2.dist-info/top_level.txt
wangph-0.0.2.dist-info/RECORD
