Metadata-Version: 2.1
Name: wangph
Version: 0.0.2
Summary: wangph lib for 3d vision
Home-page: https://github.com/AuthorityWang/wangph
Author: AuthorityWang
Author-email: wangph1@shanghaitech.edu.cn
License-File: LICENSE
